odoo/addons/stock_location_product_restriction/README.rst
odoo/addons/stock_location_product_restriction/__init__.py
odoo/addons/stock_location_product_restriction/__manifest__.py
odoo/addons/stock_location_product_restriction/hooks.py
odoo/addons/stock_location_product_restriction/i18n/es.po
odoo/addons/stock_location_product_restriction/i18n/fr.po
odoo/addons/stock_location_product_restriction/i18n/it.po
odoo/addons/stock_location_product_restriction/i18n/stock_location_product_restriction.pot
odoo/addons/stock_location_product_restriction/models/__init__.py
odoo/addons/stock_location_product_restriction/models/stock_location.py
odoo/addons/stock_location_product_restriction/models/stock_quant.py
odoo/addons/stock_location_product_restriction/readme/CONTRIBUTORS.rst
odoo/addons/stock_location_product_restriction/readme/CREDITS.rst
odoo/addons/stock_location_product_restriction/readme/DESCRIPTION.rst
odoo/addons/stock_location_product_restriction/readme/HISTORY.rst
odoo/addons/stock_location_product_restriction/readme/USAGE.rst
odoo/addons/stock_location_product_restriction/readme/newsfragments/.gitkeep
odoo/addons/stock_location_product_restriction/static/description/icon.png
odoo/addons/stock_location_product_restriction/static/description/index.html
odoo/addons/stock_location_product_restriction/tests/__init__.py
odoo/addons/stock_location_product_restriction/tests/test_stock_location.py
odoo/addons/stock_location_product_restriction/tests/test_stock_move.py
odoo/addons/stock_location_product_restriction/views/stock_location.xml
odoo_addon_stock_location_product_restriction-16.0.1.2.1.dist-info/METADATA
odoo_addon_stock_location_product_restriction-16.0.1.2.1.dist-info/WHEEL
odoo_addon_stock_location_product_restriction-16.0.1.2.1.dist-info/top_level.txt
odoo_addon_stock_location_product_restriction-16.0.1.2.1.dist-info/RECORD
